setup.py
pywechattool/__init__.py
pywechattool.egg-info/PKG-INFO
pywechattool.egg-info/SOURCES.txt
pywechattool.egg-info/dependency_links.txt
pywechattool.egg-info/not-zip-safe
pywechattool.egg-info/requires.txt
pywechattool.egg-info/top_level.txt