Metadata-Version: 1.0
Name: pywechattool
Version: 1.0.1
Summary: pywechat access_token qrcode
Home-page: https://github.com/nashuiliang
Author: chuangwang
Author-email: nashuiliang@gmail.com
License: Apache License 2.0
Keywords: pywechat access_token qrcode
Platform: UNKNOWN
